simpleloggy/simpleloggy.py
simpleloggy-1.0.dist-info/METADATA
simpleloggy-1.0.dist-info/WHEEL
simpleloggy-1.0.dist-info/top_level.txt
simpleloggy-1.0.dist-info/RECORD
