Metadata-Version: 2.1
Name: simpleloggy
Version: 1.0
Summary: Simple logger for your Python program.
Author-email: holinimofficial@outlook.com
